{
 "types": {
    "tadpole": {
        "images": {
            "egg": "pets/test-A-_0002_blue-egg.png",
            "baby": "pets/test-A-_0006_Tadpole.png",
            "adultCute": "pets/test-A-_0007_Cute-guy-1.png",
            "adultEvil": "monster_test_01-big.png"
        },
        "sounds": {
            "cryTadpole": "cry_tadpole.mp3",
            "cryFish": "cry_fish.mp3",
            "cryCutie": "cry_cutie.mp3",
            "hatch": "hatch.mp3",
            "eat": "eat.mp3",
            "swipe": "swipe_1.mp3"
        },
        "stages" : {
            "egg" : {
                "stage": "egg",
                "name": "blue egg",
                "displayName": "?? EGG ??",
                "className": "BlueEgg",
                "type": "tadpole",
                "evolveDots": 1
            },
            "baby" : {
                "stage": "baby",
                "name": "baby tadpole",
                "displayName": "Tadpole",
                "className": "Tadpole",
                "type": "tadpole",
                "evolveDots": 2
            },
            "adultCute" : {
                "stage": "adultCute",
                "name": "CuteGuy",
                "displayName": "Cute Guy",
                "className": "AdultCute",
                "type": "tadpole",
                "evolveDots": 3
            },
            "adultEvil" : {
                "stage": "adultEvil",
                "name": "evil guy",
                "displayName": "Evil Guy",
                "className": "DinoAdultEvil",
                "type": "tadpole",
                "evolveDots": 3
            }
        }
    },
    "bacteria": {
        "images": {
            "egg": "pets/test-A-_0001_green-egg.png",
            "baby": "pets/test-A-_0004_germ.png",
            "adultCute": "pets/test-A-_0004_germ.png",
            "adultEvil": "pets/test-A-_0004_germ.png"
        },
        "sounds": {
            "cryGerm": "cry_germ.mp3",
            "cryFish": "cry_fish.mp3",
            "cryCutie": "cry_cutie.mp3",
            "hatch": "hatch.mp3",
            "money": "money.mp3",
            "eat": "eat.mp3",
            "swipeTwo": "swipe_2.mp3"
        },
        "stages" : {
            "egg" : {
                "stage": "egg",
                "name": "green egg",
                "displayName": "?? EGG ??",
                "className": "GreenEgg",
                "type": "bacteria",
                "evolveDots": 1
            },
            "baby" : {
                "stage": "baby",
                "name": "bacteria",
                "displayName": "Bacteria",
                "className": "Bacteria",
                "type": "bacteria",
                "evolveDots": 2
            },
            "adultCute" : {
                "stage": "adultCute",
                "name": "Cure Bacteria",
                "displayName": "Cute Bacteria",
                "className": "AdultCute",
                "type": "bacteria",
                "evolveDots": 3
            },
            "adultEvil" : {
                "stage": "adultEvil",
                "name": "Evil Bacteria",
                "displayName": "Evil Bacteria",
                "className": "EvilBacteria",
                "type": "bacteria",
                "evolveDots": 4
            }
        }
    }
 }   
}